Metadata-Version: 2.1
Name: tlcr
Version: 0.0.2
Summary: tlcr
Home-page: https://github.com/MykolaOnyshchuk/tlcr_intensity_lib
Author: Mykola Onyshchuk
Author-email: mykolaon1@gmail.com
License: MIT
Keywords: tlcr,intensity
License-File: LICENSE
